mtbpy/__init__.py
mtbpy/mtb_command_rpc_pb2.py
mtbpy/mtb_command_rpc_pb2_grpc.py
mtbpy/mtbpy.py
mtbpy-1.0.2.dist-info/LICENSE.txt
mtbpy-1.0.2.dist-info/METADATA
mtbpy-1.0.2.dist-info/WHEEL
mtbpy-1.0.2.dist-info/top_level.txt
mtbpy-1.0.2.dist-info/RECORD
