Metadata-Version: 2.1
Name: mtbpy
Version: 1.0.2
Summary: Module for communicating with Minitab from Python scripts executed via the PYSC command.
Author-email: "Minitab, LLC" <techsupport@minitab.com>
License: MIT License
Project-URL: Homepage, https://support.minitab.com/minitab/
Classifier: Development Status :: 5 - Production/Stable
Classifier: Intended Audience :: Developers
Classifier: Intended Audience :: End Users/Desktop
Classifier: Topic :: Scientific/Engineering
Classifier: License :: OSI Approved :: MIT License
Classifier: Programming Language :: Python :: 3 :: Only
Classifier: Operating System :: OS Independent
Requires-Python: >=3.7
License-File: LICENSE.txt
Requires-Dist: protobuf >=3.20.0
Requires-Dist: grpcio >=1.57.0
